spatialpy/__init__.py
spatialpy/__version__.py
spatialpy/core/__init__.py
spatialpy/core/boundarycondition.py
spatialpy/core/cleanup.py
spatialpy/core/datafunction.py
spatialpy/core/domain.py
spatialpy/core/geometry.py
spatialpy/core/initialcondition.py
spatialpy/core/lattice.py
spatialpy/core/model.py
spatialpy/core/parameter.py
spatialpy/core/reaction.py
spatialpy/core/result.py
spatialpy/core/spatialpyerror.py
spatialpy/core/species.py
spatialpy/core/timespan.py
spatialpy/core/transformation.py
spatialpy/core/visualization.py
spatialpy/core/vtkreader.py
spatialpy/solvers/__init__.py
spatialpy/solvers/build_expression.py
spatialpy/solvers/solver.py
spatialpy/solvers/c_base/ssa_sdpd-c-simulation-engine/propensity_file_template.cpp
spatialpy/solvers/c_base/ssa_sdpd-c-simulation-engine/build/SConstruct
spatialpy/solvers/c_base/ssa_sdpd-c-simulation-engine/external/ANN/Copyright.txt
spatialpy/solvers/c_base/ssa_sdpd-c-simulation-engine/external/ANN/License.txt
spatialpy/solvers/c_base/ssa_sdpd-c-simulation-engine/external/ANN/Make-config
spatialpy/solvers/c_base/ssa_sdpd-c-simulation-engine/external/ANN/Makefile
spatialpy/solvers/c_base/ssa_sdpd-c-simulation-engine/external/ANN/ReadMe.txt
spatialpy/solvers/c_base/ssa_sdpd-c-simulation-engine/external/ANN/MS_Win32/Ann.sln
spatialpy/solvers/c_base/ssa_sdpd-c-simulation-engine/external/ANN/MS_Win32/Makefile
spatialpy/solvers/c_base/ssa_sdpd-c-simulation-engine/external/ANN/MS_Win32/ann2fig/ann2fig.vcproj
spatialpy/solvers/c_base/ssa_sdpd-c-simulation-engine/external/ANN/MS_Win32/dll/dll.vcproj
spatialpy/solvers/c_base/ssa_sdpd-c-simulation-engine/external/ANN/MS_Win32/sample/sample.vcproj
spatialpy/solvers/c_base/ssa_sdpd-c-simulation-engine/external/ANN/MS_Win32/test/test.vcproj
spatialpy/solvers/c_base/ssa_sdpd-c-simulation-engine/external/ANN/ann2fig/Makefile
spatialpy/solvers/c_base/ssa_sdpd-c-simulation-engine/external/ANN/ann2fig/ann2fig.cpp
spatialpy-1.2.2.dist-info/LICENSE
spatialpy-1.2.2.dist-info/METADATA
spatialpy-1.2.2.dist-info/WHEEL
spatialpy-1.2.2.dist-info/top_level.txt
spatialpy-1.2.2.dist-info/RECORD
