Metadata-Version: 2.1
Name: spatialpy
Version: 1.2.2
Summary: Python Interface for Spatial Stochastic Biochemical Simulations
Home-page: https://spatialpy.github.io/SpatialPy/
Download-URL: https://github.com/StochSS/SpatialPy/tarball/main/
Author: See AUTHORS
Author-email: bdrawert@unca.edu
Maintainer: See AUTHORS
Maintainer-email: bdrawert@unca.edu
License: GPL-3.0-only
Project-URL: Tracker, https://github.com/StochSS/SpatialPy/issues
Project-URL: Source, https://github.com/StochSS/SpatialPy
Keywords: biochemical simulation,Gillespie algorithm,stochastic simulation,biology,spatial simulation,RDME
Classifier: Development Status :: 5 - Production/Stable
Classifier: License :: OSI Approved :: GNU General Public License v3 (GPLv3)
Classifier: Operating System :: OS Independent
Classifier: Programming Language :: Python :: 3
Classifier: Topic :: Scientific/Engineering
Classifier: Topic :: Scientific/Engineering :: Chemistry
Classifier: Topic :: Scientific/Engineering :: Mathematics
Classifier: Topic :: Scientific/Engineering :: Medical Science Apps.
Classifier: Intended Audience :: Science/Research
License-File: LICENSE
Requires-Dist: matplotlib (>=3.0.3)
Requires-Dist: meshio (>=5.3.2)
Requires-Dist: scipy (>=1.4.1)
Requires-Dist: plotly (>=4.1.0)
Requires-Dist: scons (>=4.4.0)
